code/__init__.py
code/main.py
nubecitast-0.0.2.dist-info/LICENSE
nubecitast-0.0.2.dist-info/METADATA
nubecitast-0.0.2.dist-info/WHEEL
nubecitast-0.0.2.dist-info/top_level.txt
nubecitast-0.0.2.dist-info/RECORD
